[
  {
    "Currency": "AED",
    "Rate": "3.672896",
    "% change": "Not available"
  },
  {
    "Currency": "AFN",
    "Rate": "66.9585",
    "% change": "Not available"
  },
  {
    "Currency": "ALL",
    "Rate": "128.298385",
    "% change": "Not available"
  },
  {
    "Currency": "AMD",
    "Rate": "483.727501",
    "% change": "Not available"
  },
  {
    "Currency": "ANG",
    "Rate": "1.7762",
    "% change": "Not available"
  },
  {
    "Currency": "AOA",
    "Rate": "165.9025",
    "% change": "Not available"
  },
  {
    "Currency": "ARS",
    "Rate": "15.86875",
    "% change": "Not available"
  },
  {
    "Currency": "AUD",
    "Rate": "1.3862",
    "% change": "Not available"
  },
  {
    "Currency": "AWG",
    "Rate": "1.793333",
    "% change": "Not available"
  },
  {
    "Currency": "AZN",
    "Rate": "1.8017",
    "% change": "Not available"
  }
]
